primes_eip_f/__init__.py
primes_eip_f-2.1.dist-info/LICENSE
primes_eip_f-2.1.dist-info/METADATA
primes_eip_f-2.1.dist-info/WHEEL
primes_eip_f-2.1.dist-info/top_level.txt
primes_eip_f-2.1.dist-info/RECORD
