Metadata-Version: 2.1
Name: primes-eip-f
Version: 2.1
Summary: A tool to calculate prime numbers until n.
Home-page: UNKNOWN
Author: Fernando Sánchez
Author-email: fersanpar0@gmail.com
License: GNU GPLv3
Keywords: pyprimes mathematical operations
Platform: UNKNOWN
Classifier: Development Status :: 4 - Beta
Classifier: Intended Audience :: Developers
Classifier: Topic :: Utilities
Classifier: License :: OSI Approved :: GNU General Public License v3 (GPLv3)
Classifier: Programming Language :: Python :: 3
Classifier: Operating System :: OS Independent
License-File: LICENSE
